AUTHORS.rst
COPYING
ChangeLog.rst
MANIFEST.in
README.md
requirements.txt
setup.py
html2texttg/__init__.py
html2texttg/cli.py
html2texttg/compat.py
html2texttg/config.py
html2texttg/utils.py
html2texttg/version.py
html2texttg.egg-info/PKG-INFO
html2texttg.egg-info/SOURCES.txt
html2texttg.egg-info/dependency_links.txt
html2texttg.egg-info/entry_points.txt
html2texttg.egg-info/requires.txt
html2texttg.egg-info/top_level.txt
test/test_html2text.py
test/test_memleak.py