Metadata-Version: 2.1
Name: html2texttg
Version: 1.0.3
Summary: Turn HTML into equivalent Markdown-structured text. Telegram adapted.
Home-page: https://github.com/pavkazzz/html2text/
Author: Aaron Swartz
Author-email: me@aaronsw.com
Maintainer: Pavka Mosein
Maintainer-email: pavkazzz@mail.ru
License: GNU GPL 3
Platform: OS Independent
Classifier: Development Status :: 5 - Production/Stable
Classifier: Intended Audience :: Developers
Classifier: License :: OSI Approved :: GNU General Public License (GPL)
Classifier: Operating System :: OS Independent
Classifier: Programming Language :: Python
Classifier: Programming Language :: Python :: 3
Classifier: Programming Language :: Python :: 3.5
Classifier: Programming Language :: Python :: 3.6
Classifier: Programming Language :: Python :: 3.7
Classifier: Programming Language :: Python :: 3.8
